tvm_ffi/.gitignore
tvm_ffi/3rdparty/dlpack/include/dlpack/dlpack.h
tvm_ffi/3rdparty/libbacktrace/aclocal.m4
tvm_ffi/3rdparty/libbacktrace/alloc.c
tvm_ffi/3rdparty/libbacktrace/allocfail.c
tvm_ffi/3rdparty/libbacktrace/allocfail.sh
tvm_ffi/3rdparty/libbacktrace/atomic.c
tvm_ffi/3rdparty/libbacktrace/backtrace-supported.h.in
tvm_ffi/3rdparty/libbacktrace/backtrace.c
tvm_ffi/3rdparty/libbacktrace/backtrace.h
tvm_ffi/3rdparty/libbacktrace/btest.c
tvm_ffi/3rdparty/libbacktrace/compile
tvm_ffi/3rdparty/libbacktrace/config/enable.m4
tvm_ffi/3rdparty/libbacktrace/config/lead-dot.m4
tvm_ffi/3rdparty/libbacktrace/config/libtool.m4
tvm_ffi/3rdparty/libbacktrace/config/ltoptions.m4
tvm_ffi/3rdparty/libbacktrace/config/ltsugar.m4
tvm_ffi/3rdparty/libbacktrace/config/ltversion.m4
tvm_ffi/3rdparty/libbacktrace/config/lt~obsolete.m4
tvm_ffi/3rdparty/libbacktrace/config/multi.m4
tvm_ffi/3rdparty/libbacktrace/config/override.m4
tvm_ffi/3rdparty/libbacktrace/config/unwind_ipinfo.m4
tvm_ffi/3rdparty/libbacktrace/config/warnings.m4
tvm_ffi/3rdparty/libbacktrace/config.guess
tvm_ffi/3rdparty/libbacktrace/config.h.in
tvm_ffi/3rdparty/libbacktrace/config.sub
tvm_ffi/3rdparty/libbacktrace/configure
tvm_ffi/3rdparty/libbacktrace/configure.ac
tvm_ffi/3rdparty/libbacktrace/dwarf.c
tvm_ffi/3rdparty/libbacktrace/edtest.c
tvm_ffi/3rdparty/libbacktrace/edtest2.c
tvm_ffi/3rdparty/libbacktrace/elf.c
tvm_ffi/3rdparty/libbacktrace/fileline.c
tvm_ffi/3rdparty/libbacktrace/filenames.h
tvm_ffi/3rdparty/libbacktrace/filetype.awk
tvm_ffi/3rdparty/libbacktrace/install-debuginfo-for-buildid.sh.in
tvm_ffi/3rdparty/libbacktrace/install-sh
tvm_ffi/3rdparty/libbacktrace/instrumented_alloc.c
tvm_ffi/3rdparty/libbacktrace/internal.h
tvm_ffi/3rdparty/libbacktrace/Isaac.Newton-Opticks.txt
tvm_ffi/3rdparty/libbacktrace/LICENSE
tvm_ffi/3rdparty/libbacktrace/ltmain.sh
tvm_ffi/3rdparty/libbacktrace/macho.c
tvm_ffi/3rdparty/libbacktrace/Makefile.am
tvm_ffi/3rdparty/libbacktrace/Makefile.in
apache_tvm_ffi-0.1.8.post1.dist-info/METADATA
apache_tvm_ffi-0.1.8.post1.dist-info/WHEEL
apache_tvm_ffi-0.1.8.post1.dist-info/entry_points.txt
apache_tvm_ffi-0.1.8.post1.dist-info/licenses/LICENSE
apache_tvm_ffi-0.1.8.post1.dist-info/licenses/NOTICE
apache_tvm_ffi-0.1.8.post1.dist-info/RECORD
