Metadata-Version: 2.1
Name: apache-tvm-ffi
Version: 0.1.8.post1
Summary: tvm ffi
Keywords: machine learning,inference
Author: TVM FFI team
License: Apache 2.0
Classifier: License :: OSI Approved :: Apache Software License
Classifier: Development Status :: 4 - Beta
Classifier: Intended Audience :: Developers
Classifier: Intended Audience :: Education
Classifier: Intended Audience :: Science/Research
Project-URL: Homepage, https://github.com/apache/tvm-ffi
Project-URL: GitHub, https://github.com/apache/tvm-ffi
Requires-Python: >=3.8
Requires-Dist: typing-extensions>=4.5
Provides-Extra: torch
Requires-Dist: torch; extra == "torch"
Requires-Dist: setuptools; extra == "torch"
Requires-Dist: ninja; extra == "torch"
Provides-Extra: cpp
Requires-Dist: ninja; extra == "cpp"
Provides-Extra: test
Requires-Dist: pytest; extra == "test"
Requires-Dist: numpy; extra == "test"
Requires-Dist: ninja; extra == "test"
Requires-Dist: torch; python_version < "3.14" and extra == "test"
Requires-Dist: setuptools; extra == "test"
